{
  "trainings": [
    {
      "schoolName": "Lannion Institute of Technology",
      "certificateName": "BUT Informatique (Computer Science Bachelor's degree)",
      "specialty": "Data administration, management, and operation",
      "description": "The BUT Informatique is a three-year program that trains computer scientists to design, develop, and maintain computer applications in consultation with users, while ensuring the proper functioning of computer systems.",
      "startDate": "2023-09-01",
      "endDate": "2026-05-30",
      "url": "https://iut-lannion.univ-rennes.fr/computer-science-information-technology"
    }
  ]
}